README.md
setup.py
flask_ipywidgets/__init__.py
flask_ipywidgets/_version.py
flask_ipywidgets/example1.py
flask_ipywidgets/example2.py
flask_ipywidgets/kernel.py
flask_ipywidgets.egg-info/PKG-INFO
flask_ipywidgets.egg-info/SOURCES.txt
flask_ipywidgets.egg-info/dependency_links.txt
flask_ipywidgets.egg-info/not-zip-safe
flask_ipywidgets.egg-info/requires.txt
flask_ipywidgets.egg-info/top_level.txt
flask_ipywidgets/static/bootstrap.min.css
flask_ipywidgets/static/embed-amd.js
flask_ipywidgets/static/index.html
flask_ipywidgets/static/main.js
flask_ipywidgets/static/require.min.js
flask_ipywidgets/static/dist/0.libwidgets.js
flask_ipywidgets/static/dist/0.libwidgets.js.map
flask_ipywidgets/static/dist/1.libwidgets.js
flask_ipywidgets/static/dist/1.libwidgets.js.map
flask_ipywidgets/static/dist/674f50d287a8c48dc19ba404d20fe713.eot
flask_ipywidgets/static/dist/912ec66d7572ff821749319396470bde.svg
flask_ipywidgets/static/dist/af7ae505a9eed503f8b8e6982036873e.woff2
flask_ipywidgets/static/dist/b06871f281fee6b241d60582ae9369b9.ttf
flask_ipywidgets/static/dist/fee66e712a8a08eef5805a46892932ad.woff
flask_ipywidgets/static/dist/ipysheet.js
flask_ipywidgets/static/dist/libwidgets.js
flask_ipywidgets/static/dist/libwidgets.js.map
flask_ipywidgets/static/dist/@jupyter-widgets/base.js
flask_ipywidgets/static/dist/@jupyter-widgets/controls.js
flask_ipywidgets/templates/example1.html
flask_ipywidgets/templates/example2.html