Metadata-Version: 1.0
Name: flask-ipywidgets
Version: 0.1.0
Summary: Ipywidget in your Flask webserver
Home-page: UNKNOWN
Author: Maarten Breddels
Author-email: maartenbreddels@gmail.com
License: UNKNOWN
Keywords: ipython,jupyter,widgets
Platform: UNKNOWN
